pysportsdb/__init__.py
pysportsdb/api_spec.py
pysportsdb/cli.py
pysportsdb/client.py
pysportsdb/constants.py
pysportsdb/exceptions.py
pysportsdb-0.1.0.dist-info/WHEEL
pysportsdb-0.1.0.dist-info/METADATA
pysportsdb-0.1.0.dist-info/RECORD
