Metadata-Version: 2.1
Name: pysportsdb
Version: 0.1.0
Summary: An simple Python interface to thesportsdb.com's API
License: MIT
Author: Colin Powell
Author-email: colin@unbl.ink
Requires-Python: >=3.7,<4.0
Classifier: License :: OSI Approved :: MIT License
Classifier: Programming Language :: Python :: 3
Classifier: Programming Language :: Python :: 3.7
Classifier: Programming Language :: Python :: 3.8
Classifier: Programming Language :: Python :: 3.9
Classifier: Programming Language :: Python :: 3.10
Classifier: Programming Language :: Python :: 3.11
Requires-Dist: mock (>=5.0.1,<6.0.0)
Requires-Dist: requests (>=2.28.2,<3.0.0)
